gemini_ng/__init__.py
gemini_ng/chat.py
gemini_ng/client.py
gemini_ng/schemas/__init__.py
gemini_ng/schemas/base.py
gemini_ng/schemas/harm.py
gemini_ng/schemas/part.py
gemini_ng/schemas/proxy.py
gemini_ng/schemas/request.py
gemini_ng/schemas/response.py
gemini_ng/schemas/upload.py
gemini_ng/utils/__init__.py
gemini_ng/utils/cache.py
gemini_ng/utils/error.py
gemini_ng/utils/video.py
gemini_ng-0.1.4.dist-info/LICENSE
gemini_ng-0.1.4.dist-info/METADATA
gemini_ng-0.1.4.dist-info/WHEEL
gemini_ng-0.1.4.dist-info/top_level.txt
gemini_ng-0.1.4.dist-info/RECORD
