Metadata-Version: 2.1
Name: gemini-ng
Version: 0.1.4
Summary: Next-generation Gemini API Client
Author-email: Ming Yang <ymviv@qq.com>
License: Copyright (c) 2024 Ming Yang
Project-URL: Documentation, https://github.com/vivym/gemini-ng#readme
Project-URL: Issues, https://github.com/vivym/gemini-ng/issues
Project-URL: Source, https://github.com/vivym/gemini-ng
Keywords: Gemini
Classifier: Development Status :: 4 - Beta
Classifier: Programming Language :: Python
Classifier: Programming Language :: Python :: 3.11
Classifier: Programming Language :: Python :: Implementation :: CPython
Requires-Python: >=3.11
License-File: LICENSE
Requires-Dist: google-api-python-client >=2.125.0
Requires-Dist: requests >=2.31.0
Requires-Dist: pydantic >=2.7.0
Requires-Dist: av >=12.0.0
Requires-Dist: pillow >=10.3.0
Requires-Dist: numpy >=1.26.4
Requires-Dist: tqdm >=4.66.2
Requires-Dist: diskcache >=5.6.3
